c_lancet/__init__.py
c_lancet/file.py
c_lancet/func.py
c_lancet/proj.py
c_lancet/structure.py
c_lancet/tree-sitter.so
c_lancet/utils.py
c_lancet-0.0.1.dist-info/LICENSE
c_lancet-0.0.1.dist-info/METADATA
c_lancet-0.0.1.dist-info/WHEEL
c_lancet-0.0.1.dist-info/top_level.txt
c_lancet-0.0.1.dist-info/RECORD
